extras/__init__.py
extras/divide.py
extras/multiply.py
sagar_module-0.1.dist-info/METADATA
sagar_module-0.1.dist-info/WHEEL
sagar_module-0.1.dist-info/top_level.txt
sagar_module-0.1.dist-info/RECORD
